<?xml version='1.0' encoding="windows-1251"?>

<xml>
	
	<!-------------------------- FREEDOM TRADER ------------------------>
    <specific_character id="mil_smart_terrain_7_10_freedom_trader_stalker" team_default="1">
    <name>mil_Svoboda_trader_name</name>
    <icon>ui_npc_u_stalker_sv_balon_1</icon>
    <bio>ќпытный сталкер. ƒетальна¤ информаци¤ отсутствует.</bio>

    <class>mil_smart_terrain_7_10_freedom_trader_stalker</class>
    <community>trader</community>
    
    <rank>900</rank>
    <reputation>100</reputation>
	 <money min="100000" max="100000" infinitive="1"/>
    <visual>actors\svoboda\stalker_sv_balon_1</visual>
	<snd_config>characters_voice\human_02\freedom\</snd_config>

   <supplies>
			[spawn] \n
			wpn_sig220 \n
			ammo_11.43x23_hydro = 1 \n
			wpn_sig550 \n
			ammo_5.56x45_ap = 1 \n
		</supplies>

#include "gameplay\character_criticals_5.xml"
	<actor_dialog>actor_break_dialog</actor_dialog>
  </specific_character>

  <!-------------------------- FREEDOM MECHANIC ------------------------>
  <specific_character id="mil_smart_terrain_7_7_freedom_mechanic_stalker" team_default="1">
    <name>mil_Svoboda_engineer_name</name>
	<icon>ui_npc_u_stalker_sv_rukzak_3</icon>
    <bio>ќпытный сталкер. ƒетальна¤ информаци¤ отсутствует.</bio>

    <class>mil_smart_terrain_7_7_freedom_mechanic_stalker</class>
    <community>trader</community>
	<mechanic_mode>1</mechanic_mode>
    
    <rank>901</rank>
    <reputation>101</reputation>
	<visual>actors\svoboda\stalker_sv_rukzak_3</visual>
	<snd_config>characters_voice\human_01\freedom\</snd_config>

    <supplies>
			[spawn] \n
			wpn_walther \n
			ammo_9x19_pbp \n
			wpn_sig550 = 1 \n
			ammo_5.56x45_ap = 1 \n
#include "gameplay\character_items.xml" \n
#include "gameplay\character_drugs.xml" \n
#include "gameplay\character_food.xml"			
		</supplies>
#include "gameplay\character_criticals_4.xml"
	<actor_dialog>actor_break_dialog</actor_dialog>
  </specific_character>

</xml>