<?xml version="1.0" encoding="windows-1251" ?>
<game_dialogs>
<!------------------ bar_visitors_barman_stalker_trader ----------->
    <dialog id="bar_visitors_barman_stalker_trader_start_dialog">
        <phrase_list>
            <phrase id="1">
                <text />
                <next>11</next>
                <next>12</next>
                <next>13</next>
            </phrase>
            <phrase id="0">
                <text />
                <next>1</next>
            </phrase>
            <phrase id="13">
                <text>bar_visitors_barman_stalker_trader_start_dialog_13</text>
            </phrase>
            <phrase id="12">
                <text>bar_visitors_barman_stalker_trader_start_dialog_12</text>
            </phrase>
            <phrase id="11">
                <text>bar_visitors_barman_stalker_trader_start_dialog_11</text>
            </phrase>
        </phrase_list>
    </dialog>
<!------------- bar_visitors_stalker_mechanic ---------->
    <dialog id="bar_visitors_stalker_mechanic_start_dialog">
        <phrase_list>
			<phrase id="0">
                <text>bar_visitors_stalker_mechanic_start_dialog_1</text>
            </phrase>
        </phrase_list>
    </dialog>
</game_dialogs>
