<?xml version='1.0' encoding="windows-1251"?>

<game_information_portions>

    <info_portion id="">mar_intro_scene_2_end</info_portion>
	<info_portion id="">mar_intro_scene_2_cameff_end</info_portion>
	<info_portion id="">red_forester_who_are_you</info_portion>
	<info_portion id="">bar_deactivate_radar_done</info_portion>
	<info_portion id="">yantar_attack_start</info_portion>
	
	<!-- Lab X16 switchers -->
	<info_portion id="">yan_labx16_switcher_1_off</info_portion>
	<info_portion id="">yan_labx16_switcher_2_off</info_portion>
	<info_portion id="">yan_labx16_switcher_3_off</info_portion>
    <info_portion id="">yan_labx16_switcher_primary_off</info_portion>
	
	<info_portion id="">yan_labx16_switcher_1_end</info_portion>
	<info_portion id="">yan_labx16_switcher_2_end</info_portion>
	<info_portion id="">yan_labx16_switcher_3_end</info_portion>
	<info_portion id="">yan_labx16_switcher_primary_try</info_portion>
	
	<info_portion id="">agru_controller_death</info_portion>
	<info_portion id="">agru_phisics_active_1</info_portion>
	
</game_information_portions>