<?xml version="1.0" encoding="windows-1251" ?>
<string_table>
	<!-- cit_killers_merc_mechanic_stalker -->
	<string id="cit_killers_merc_mechanic_stalker_task_1_name">
		<text>Find %s</text>
	</string>
	<string id="cit_killers_merc_mechanic_stalker_task_1_text">
		<text>You have been asked to retrieve a %s. Bring it back to Toad if you happen to get your hands on one.</text>
	</string>
	<string id="cit_killers_merc_mechanic_stalker_task_1_about">
		<text>I have a proposition for you. If you can bring me some new tools, you will receive payment. Are you up for it?</text>
	</string>
	<string id="cit_killers_merc_mechanic_stalker_task_1_fetch_about">
		<text>Good. I've been looking all over for a %s. It should contain some oils and tools I need to do work on firearms. I will pay you for one of these toolkits if you can bring a full set back to me.</text>
	</string>
	<string id="cit_killers_merc_mechanic_stalker_task_1_fetch_finish">
		<text>Right, on. This is what I've been looking for, thank!</text>
	</string>
	<string id="cit_killers_merc_mechanic_stalker_task_2_name">
		<text>Find %s</text>
	</string>
	<string id="cit_killers_merc_mechanic_stalker_task_2_text">
		<text>You have been asked to retrieve a %s. He needs more advanced tools to perform even better upgrades. Bring it back to Toad if you happen to get your hands on one.</text>
	</string>
	<string id="cit_killers_merc_mechanic_stalker_task_2_about">
		<text>I have another proposition. The toolset you brought me is working out good, but it doesn't have everything I need. Do you think you can find me a better set?</text>
	</string>
	<string id="cit_killers_merc_mechanic_stalker_task_2_fetch_about">
		<text>I need an %s. I'm not sure where you can get one of these, but if you can find one, I need it.</text>
	</string>
	<string id="cit_killers_merc_mechanic_stalker_task_2_fetch_finish">
		<text>Everything I need is here. Thank you.</text>
	</string>	
</string_table>
